odoo/addons/delivery_carrier_label_postlogistics/README.rst
odoo/addons/delivery_carrier_label_postlogistics/__init__.py
odoo/addons/delivery_carrier_label_postlogistics/__manifest__.py
odoo/addons/delivery_carrier_label_postlogistics/data/barcode handbuch.PDF
odoo/addons/delivery_carrier_label_postlogistics/data/barcode_v2_3.wsdl
odoo/addons/delivery_carrier_label_postlogistics/data/barcode_v2_3.xsd
odoo/addons/delivery_carrier_label_postlogistics/data/delivery.xml
odoo/addons/delivery_carrier_label_postlogistics/data/partner.xml
odoo/addons/delivery_carrier_label_postlogistics/data/product.xml
odoo/addons/delivery_carrier_label_postlogistics/i18n/am.po
odoo/addons/delivery_carrier_label_postlogistics/i18n/ar.po
odoo/addons/delivery_carrier_label_postlogistics/i18n/ca.po
odoo/addons/delivery_carrier_label_postlogistics/i18n/cs.po
odoo/addons/delivery_carrier_label_postlogistics/i18n/de.po
odoo/addons/delivery_carrier_label_postlogistics/i18n/delivery_carrier_label_postlogistics.pot
odoo/addons/delivery_carrier_label_postlogistics/i18n/el_GR.po
odoo/addons/delivery_carrier_label_postlogistics/i18n/en.po
odoo/addons/delivery_carrier_label_postlogistics/i18n/es.po
odoo/addons/delivery_carrier_label_postlogistics/i18n/es_CR.po
odoo/addons/delivery_carrier_label_postlogistics/i18n/es_EC.po
odoo/addons/delivery_carrier_label_postlogistics/i18n/es_ES.po
odoo/addons/delivery_carrier_label_postlogistics/i18n/es_MX.po
odoo/addons/delivery_carrier_label_postlogistics/i18n/es_VE.po
odoo/addons/delivery_carrier_label_postlogistics/i18n/et.po
odoo/addons/delivery_carrier_label_postlogistics/i18n/fi.po
odoo/addons/delivery_carrier_label_postlogistics/i18n/fr.po
odoo/addons/delivery_carrier_label_postlogistics/i18n/gl.po
odoo/addons/delivery_carrier_label_postlogistics/i18n/hr_HR.po
odoo/addons/delivery_carrier_label_postlogistics/i18n/it.po
odoo/addons/delivery_carrier_label_postlogistics/i18n/lt.po
odoo/addons/delivery_carrier_label_postlogistics/i18n/nl.po
odoo11_addon_delivery_carrier_label_postlogistics-11.0.1.0.0.99.dev12.dist-info/METADATA
odoo11_addon_delivery_carrier_label_postlogistics-11.0.1.0.0.99.dev12.dist-info/WHEEL
odoo11_addon_delivery_carrier_label_postlogistics-11.0.1.0.0.99.dev12.dist-info/top_level.txt
odoo11_addon_delivery_carrier_label_postlogistics-11.0.1.0.0.99.dev12.dist-info/RECORD
