Metadata-Version: 2.1
Name: odoo11-addon-delivery-carrier-label-postlogistics
Version: 11.0.1.0.0.99.dev12
Summary: Print postlogistics shipping labels
Home-page: https://github.com/OCA/delivery-carrier
Author: Camptocamp,Odoo Community Association (OCA)
Author-email: support@odoo-community.org
License: AGPL-3
Platform: UNKNOWN
Classifier: Programming Language :: Python
Classifier: Framework :: Odoo
Classifier: Framework :: Odoo :: 11.0
Classifier: License :: OSI Approved :: GNU Affero General Public License v3
Requires-Python: >=2.7, !=3.0.*, !=3.1.*, !=3.2.*, !=3.3.*, !=3.4.*
Requires-Dist: odoo11-addon-base-delivery-carrier-label
Requires-Dist: odoo11-addon-configuration-helper
Requires-Dist: odoo <11.1dev,>=11.0a
Requires-Dist: suds-jurko
